rustc_t_x64_win_msvc_nightly_p4/__init__.py
rustc_t_x64_win_msvc_nightly_p4/data/rustc_driver-00a065e462aa96d9.dll
rustc_t_x64_win_msvc_nightly_p4-1.91.0.dist-info/METADATA
rustc_t_x64_win_msvc_nightly_p4-1.91.0.dist-info/WHEEL
rustc_t_x64_win_msvc_nightly_p4-1.91.0.dist-info/top_level.txt
rustc_t_x64_win_msvc_nightly_p4-1.91.0.dist-info/RECORD
